membit/__init__.py
membit/async_membit.py
membit/constants.py
membit/errors.py
membit/membit.py
membit_python-0.0.2.dist-info/METADATA
membit_python-0.0.2.dist-info/WHEEL
membit_python-0.0.2.dist-info/licenses/LICENSE
membit_python-0.0.2.dist-info/RECORD
