Metadata-Version: 2.4
Name: membit-python
Version: 0.0.2
Summary: Python client for the Membit API
License-File: LICENSE
Requires-Python: >=3.10
Requires-Dist: httpx>=0.28.1
Requires-Dist: requests>=2.25.0
